{"otherData": {},"traceEvents":[{"cat":"function","dur":-7.7032957,"name":"FreeMemory Shader - 'editorFiles/shaders/2D/defaultSprite.glsl'","ph":"X","pid":0,"tid":0,"ts":7.7032957},{"cat":"function","dur":-7.7035694,"name":"FreeMemory Shader - 'editorFiles/shaders/3D/pbrTest.glsl'","ph":"X","pid":0,"tid":0,"ts":7.7035694},{"cat":"function","dur":-7.703679,"name":"FreeMemory Shader - 'editorFiles/shaders/debug/debugLineShader.glsl'","ph":"X","pid":0,"tid":0,"ts":7.703679},{"cat":"function","dur":-7.7031403,"name":"AssetPool FreeMemory","ph":"X","pid":0,"tid":0,"ts":7.7031403},{"cat":"function","dur":-7.6995587,"name":"Close Window","ph":"X","pid":0,"tid":0,"ts":7.6995587}]}